{
  "Login": "",
  "Throw Error": "",
  "admin_panel": "",
  "all_articles": "",
  "articles_not_found": "",
  "by": "",
  "close": "",
  "comments": "",
  "create_article": "",
  "create_new_article": "",
  "created_date": "",
  "decrement": "",
  "descending": "",
  "economic": "",
  "edit_article_with_id": "",
  "enter_comment_text": "",
  "enter_password": "",
  "enter_username": "",
  "forbidden_pag_title": "",
  "increasing": "",
  "increment": "",
  "it": "",
  "login": "",
  "login_form": "",
  "logout": "",
  "main_page": "",
  "name": "",
  "no_comments": "",
  "open": "",
  "page_not_found": "",
  "profile": "",
  "read_more": "",
  "recommends": "",
  "reload_page": "",
  "science": "",
  "search": "",
  "select_country": "",
  "select_currency": "",
  "send": "",
  "sort_by": "",
  "thanks_for_feedback": "",
  "unexpected_error_happened": "",
  "value": "",
  "views": "",
  "wrong_auth_data": "",
  "your_feedback": "",
  "Оставьте свой отзыв о статье, это поможет улучшить качество": "",
  "Оцените статью": "",
  "Ошибка при загрузке статей": "",
  "Произошла ошибка при загрузке статьи": {
    "": ""
  }
}
